LICENSE
MANIFEST.in
README.md
README.rst
setup.cfg
setup.py
KernelUpgrader.egg-info/PKG-INFO
KernelUpgrader.egg-info/SOURCES.txt
KernelUpgrader.egg-info/dependency_links.txt
KernelUpgrader.egg-info/entry_points.txt
KernelUpgrader.egg-info/not-zip-safe
KernelUpgrader.egg-info/requires.txt
KernelUpgrader.egg-info/top_level.txt
kernel_upgrader/__init__.py
kernel_upgrader/data_manager/__init__.py
kernel_upgrader/exceptions/__init__.py
kernel_upgrader/net/DependenciesInstaller.py
kernel_upgrader/net/Downloader.py
kernel_upgrader/net/KernelVersions.py
kernel_upgrader/net/PageInfo.py
kernel_upgrader/net/__init__.py
kernel_upgrader/utils/__init__.py
kernel_upgrader/utils/anim.py
kernel_upgrader/utils/colors.py
kernel_upgrader/utils/logger.py
kernel_upgrader/values/Constants.py
kernel_upgrader/values/__init__.py